numpyx/__init__.py
numpyx/numpyx.cp39-win32.pyd
numpyx/numpyx.pyi
numpyx/py.typed
numpyx-1.6.0.dist-info/licenses/LICENSE.txt
numpyx-1.6.0.dist-info/METADATA
numpyx-1.6.0.dist-info/WHEEL
numpyx-1.6.0.dist-info/top_level.txt
numpyx-1.6.0.dist-info/RECORD
