Metadata-Version: 2.4
Name: numpyx
Version: 1.6.0
Summary: Utility functions for numpy, written in cython
Home-page: https://github.com/gesellkammer/numpyx
Download-URL: https://github.com/gesellkammer/numpyx
Author: eduardo moguillansky
Author-email: eduardo.moguillansky@gmail.com
License: GPL v3
Classifier: Intended Audience :: Developers
Classifier: License :: OSI Approved :: BSD License
Classifier: Natural Language :: English
Classifier: Programming Language :: Python :: 3
Requires-Python: >=3.9
License-File: LICENSE.txt
Requires-Dist: numpy>=2
Dynamic: author
Dynamic: author-email
Dynamic: classifier
Dynamic: description
Dynamic: download-url
Dynamic: home-page
Dynamic: license
Dynamic: license-file
Dynamic: requires-dist
Dynamic: requires-python
Dynamic: summary
